newertype/__init__.py
newertype/newertype.py
newertype/py.typed
newertype-0.3.0.dist-info/METADATA
newertype-0.3.0.dist-info/WHEEL
newertype-0.3.0.dist-info/licenses/LICENSE
newertype-0.3.0.dist-info/RECORD
