Metadata-Version: 2.4
Name: newertype
Version: 0.3.0
Summary: An Implementation of the NewType Pattern for Python that works in dynamic contexts.
Project-URL: homepage, https://github.com/evanjpw/newertype
Project-URL: repository, https://github.com/evanjpw/newertype
Project-URL: issues, https://github.com/evanjpw/newertype/issues
Project-URL: changelog, https://github.com/evanjpw/newertype/blob/main/CHANGELOG.md
Author-email: Evan Williams <evanjpw@gmail.com>
License-Expression: MIT
License-File: LICENSE
Keywords: newtype,python,runtime,type-safety,typechecker,typehints,typing
Classifier: Development Status :: 5 - Production/Stable
Classifier: Intended Audience :: Developers
Classifier: License :: OSI Approved :: MIT License
Classifier: Programming Language :: Python :: 3 :: Only
Classifier: Programming Language :: Python :: 3.8
Classifier: Programming Language :: Python :: 3.9
Classifier: Programming Language :: Python :: 3.10
Classifier: Programming Language :: Python :: 3.11
Classifier: Programming Language :: Python :: 3.12
Classifier: Programming Language :: Python :: 3.13
Classifier: Topic :: Software Development :: Libraries :: Python Modules
Requires-Python: >=3.8
Provides-Extra: dev
Requires-Dist: isort>=5.13.2; extra == 'dev'
Requires-Dist: pre-commit>=3.5.0; extra == 'dev'
Requires-Dist: pytest-cov>=5.0.0; extra == 'dev'
Requires-Dist: pytest>=7.0.0; extra == 'dev'
Requires-Dist: ruff>=0.13.3; extra == 'dev'
